pangtreebuild/__init__.py
pangtreebuild/__main__.py
pangtreebuild/logging.conf
pangtreebuild/affinity_tree/__init__.py
pangtreebuild/affinity_tree/builders.py
pangtreebuild/affinity_tree/parameters.py
pangtreebuild/affinity_tree/poa.py
pangtreebuild/affinity_tree/tree.py
pangtreebuild/affinity_tree/bin/blosum80.mat
pangtreebuild/affinity_tree/bin/poa
pangtreebuild/mafgraph/__init__.py
pangtreebuild/mafgraph/mafreader.py
pangtreebuild/mafgraph/sorter.py
pangtreebuild/mafgraph/weighted_edges.py
pangtreebuild/mafgraph/graph/Arc.py
pangtreebuild/mafgraph/graph/Block.py
pangtreebuild/mafgraph/graph/EdgeInfo.py
pangtreebuild/mafgraph/graph/SequenceInfo.py
pangtreebuild/mafgraph/graph/__init__.py
pangtreebuild/pangenome/DAGMaf.py
pangtreebuild/pangenome/__init__.py
pangtreebuild/pangenome/builder.py
pangtreebuild/pangenome/graph.py
pangtreebuild/pangenome/builders/__init__.py
pangtreebuild/pangenome/builders/dagmaf2poagraph.py
pangtreebuild/pangenome/builders/maf2dagmaf.py
pangtreebuild/pangenome/builders/maf2poagraph.py
pangtreebuild/pangenome/builders/po2poagraph.py
pangtreebuild/pangenome/parameters/__init__.py
pangtreebuild/pangenome/parameters/missings.py
pangtreebuild/pangenome/parameters/msa.py
pangtreebuild/serialization/__init__.py
pangtreebuild/serialization/fasta.py
pangtreebuild/serialization/json.py
pangtreebuild/serialization/po.py
pangtreebuild/tests/__init__.py
pangtreebuild/tests/__pycache__/__init__.cpython-38.pyc
pangtreebuild/tests/__pycache__/context.cpython-38.pyc
pangtreebuild/tests/__pycache__/tests_bla.cpython-38.pyc
pangtreebuild/tests/tests_affinity_tree/__init__.py
pangtreebuild/tests/tests_affinity_tree/tests_POTranslator.py
pangtreebuild/tests/tests_affinity_tree/tests_affinity.py
pangtreebuild/tests/tests_affinity_tree/__pycache__/__init__.cpython-38.pyc
pangtreebuild/tests/tests_affinity_tree/__pycache__/tests_POTranslator.cpython-38.pyc
pangtreebuild/tests/tests_affinity_tree/__pycache__/tests_affinity.cpython-38.pyc
pangtreebuild-1.0.3.dist-info/LICENSE
pangtreebuild-1.0.3.dist-info/METADATA
pangtreebuild-1.0.3.dist-info/WHEEL
pangtreebuild-1.0.3.dist-info/top_level.txt
pangtreebuild-1.0.3.dist-info/RECORD
