Metadata-Version: 2.1
Name: pangtreebuild
Version: 1.0.3
Summary: Multiple sequence alignment analysis with Affinity Tree generation
Home-page: https://github.com/meoke/pangtree
Author: Paulina Dziadkiewicz
Author-email: pedziadkiewicz@gmail.com
License: MIT Licence
Platform: UNKNOWN
Classifier: Programming Language :: Python :: 3
Classifier: License :: OSI Approved :: MIT License
Classifier: Operating System :: POSIX :: Linux
Classifier: Topic :: Scientific/Engineering :: Bio-Informatics
Requires-Dist: biopython
Requires-Dist: numpy
Requires-Dist: jsonpickle
Requires-Dist: ddt
Requires-Dist: networkx
Requires-Dist: six
Requires-Dist: newick
